libresign/__init__.py
libresign/config.py
libresign/flaskapp.py
libresign/infoscreen.py
libresign/locontrol.py
libresign/playlist.py
libresign/request.py
libresign/sdremote.py
libresign/signd.py
libresign/unoremote.py
libresign/web.py
libresign/static/bg_blue.jpg
libresign/static/html5sortable.js
libresign/static/css/.style.css.swp
libresign/static/css/style.css
libresign/templates/.index.html.swp
libresign/templates/base.html
libresign/templates/index.html
libresign/templates/macros.html
libresign-1.0.2.data/scripts/libresign
src/__init__.py
src/config.py
src/flaskapp.py
src/infoscreen.py
src/locontrol.py
src/playlist.py
src/request.py
src/sdremote.py
src/signd.py
src/unoremote.py
src/web.py
libresign-1.0.2.dist-info/COPYING.MPL
libresign-1.0.2.dist-info/METADATA
libresign-1.0.2.dist-info/WHEEL
libresign-1.0.2.dist-info/top_level.txt
libresign-1.0.2.dist-info/RECORD
